polars_list_utils-0.14.0.dist-info/METADATA
polars_list_utils-0.14.0.dist-info/WHEEL
polars_list_utils/__init__.py
polars_list_utils/_internal.abi3.so
polars_list_utils-0.14.0.dist-info/RECORD
