Metadata-Version: 2.4
Name: polars-list-utils
Version: 0.14.0
Classifier: Programming Language :: Rust
Classifier: Programming Language :: Python :: 3
Classifier: Programming Language :: Python :: Implementation :: CPython
Classifier: Programming Language :: Python :: Implementation :: PyPy
Classifier: Operating System :: OS Independent
Requires-Dist: polars>=1.23.0
Requires-Dist: maturin>=1.0,<2.0 ; extra == 'dev'
Requires-Dist: numpy>=2.2.3 ; extra == 'dev'
Requires-Dist: matplotlib>=3.4.0 ; extra == 'dev'
Provides-Extra: dev
Summary: Utilities for working with List columns in Polars
Author-email: Travis Hammond <dashdeckers@gmail.com>
Requires-Python: >=3.10, <=3.12
